lab08/fibonacci_generator.v
module fibonacci_generator (
    input clk,        
    input rst,       
    input enable,     
    output reg [31:0] fib_out  
);

    reg [31:0] fib_prev1;  
    reg [31:0] fib_prev2; 

    always @(posedge clk or posedge rst) begin
        if (rst) begin
            // Initialize Fibonacci numbers
            fib_prev1 <= 32'd1;  
            fib_prev2 <= 32'd0;  
            fib_out <= 32'd0; 
        end else if (enable) begin
            // Compute next Fibonacci number
            fib_out <= fib_prev1 + fib_prev2;

            // Update previous Fibonacci numbers
            fib_prev2 <= fib_prev1;
            fib_prev1 <= fib_out;
        end
    end

endmodule

lab08/fibonacci_trace.vcd
$version Generated by VerilatedVcd $end
$timescale 1ps $end
 $scope module TOP $end
  $var wire 1 # clk $end
  $var wire 1 $ rst $end
  $var wire 1 % enable $end
  $var wire 32 & fib_out [31:0] $end
  $scope module fibonacci_generator $end
   $var wire 1 # clk $end
   $var wire 1 $ rst $end
   $var wire 1 % enable $end
   $var wire 32 & fib_out [31:0] $end
   $var wire 32 ' fib_prev1 [31:0] $end
   $var wire 32 ( fib_prev2 [31:0] $end
  $upscope $end
 $upscope $end
$enddefinitions $end


#0
1#
1$
1%
b00000000000000000000000000000000 &
b00000000000000000000000000000000 '
b00000000000000000000000000000000 (
#1
0#
#2
1#
b00000000000000000000000000000001 '
#3
0#
#4
1#
#5
0#
#6
1#
#7
0#
#8
1#
#9
0#
#10
1#
0$
b00000000000000000000000000000001 &
b00000000000000000000000000000000 '
b00000000000000000000000000000001 (
#11
0#
#12
1#
b00000000000000000000000000000001 '
b00000000000000000000000000000000 (
#13
0#
#14
1#
b00000000000000000000000000000001 (
#15
0#
#16
1#
b00000000000000000000000000000010 &
#17
0#
#18
1#
b00000000000000000000000000000010 '
#19
0#
#20
1#
b00000000000000000000000000000011 &
b00000000000000000000000000000010 (
#21
0#
#22
1#
b00000000000000000000000000000100 &
b00000000000000000000000000000011 '
#23
0#
#24
1#
b00000000000000000000000000000101 &
b00000000000000000000000000000100 '
b00000000000000000000000000000011 (
#25
0#
#26
1#
b00000000000000000000000000000111 &
b00000000000000000000000000000101 '
b00000000000000000000000000000100 (
#27
0#
#28
1#
b00000000000000000000000000001001 &
b00000000000000000000000000000111 '
b00000000000000000000000000000101 (
#29
0#
#30
1#
b00000000000000000000000000001100 &
b00000000000000000000000000001001 '
b00000000000000000000000000000111 (
#31
0#
#32
1#
b00000000000000000000000000010000 &
b00000000000000000000000000001100 '
b00000000000000000000000000001001 (
#33
0#
#34
1#
b00000000000000000000000000010101 &
b00000000000000000000000000010000 '
b00000000000000000000000000001100 (
#35
0#
#36
1#
b00000000000000000000000000011100 &
b00000000000000000000000000010101 '
b00000000000000000000000000010000 (
#37
0#
#38
1#
b00000000000000000000000000100101 &
b00000000000000000000000000011100 '
b00000000000000000000000000010101 (
#39
0#
#40
1#
b00000000000000000000000000110001 &
b00000000000000000000000000100101 '
b00000000000000000000000000011100 (
#41
0#
#42
1#
b00000000000000000000000001000001 &
b00000000000000000000000000110001 '
b00000000000000000000000000100101 (
#43
0#
#44
1#
b00000000000000000000000001010110 &
b00000000000000000000000001000001 '
b00000000000000000000000000110001 (
#45
0#
#46
1#
b00000000000000000000000001110010 &
b00000000000000000000000001010110 '
b00000000000000000000000001000001 (
#47
0#
#48
1#
b00000000000000000000000010010111 &
b00000000000000000000000001110010 '
b00000000000000000000000001010110 (
#49
0#
#50
1#
b00000000000000000000000011001000 &
b00000000000000000000000010010111 '
b00000000000000000000000001110010 (
#51
0#
#52
1#
b00000000000000000000000100001001 &
b00000000000000000000000011001000 '
b00000000000000000000000010010111 (
#53
0#
#54
1#
b00000000000000000000000101011111 &
b00000000000000000000000100001001 '
b00000000000000000000000011001000 (
#55
0#
#56
1#
b00000000000000000000000111010001 &
b00000000000000000000000101011111 '
b00000000000000000000000100001001 (
#57
0#
#58
1#
b00000000000000000000001001101000 &
b00000000000000000000000111010001 '
b00000000000000000000000101011111 (
#59
0#
#60
1#
b00000000000000000000001100110000 &
b00000000000000000000001001101000 '
b00000000000000000000000111010001 (
#61
0#
#62
1#
b00000000000000000000010000111001 &
b00000000000000000000001100110000 '
b00000000000000000000001001101000 (
#63
0#
#64
1#
b00000000000000000000010110011000 &
b00000000000000000000010000111001 '
b00000000000000000000001100110000 (
#65
0#
#66
1#
b00000000000000000000011101101001 &
b00000000000000000000010110011000 '
b00000000000000000000010000111001 (
#67
0#
#68
1#
b00000000000000000000100111010001 &
b00000000000000000000011101101001 '
b00000000000000000000010110011000 (
#69
0#
#70
1#
b00000000000000000000110100000001 &
b00000000000000000000100111010001 '
b00000000000000000000011101101001 (
#71
0#
#72
1#
b00000000000000000001000100111010 &
b00000000000000000000110100000001 '
b00000000000000000000100111010001 (
#73
0#
#74
1#
b00000000000000000001011011010010 &
b00000000000000000001000100111010 '
b00000000000000000000110100000001 (
#75
0#
#76
1#
b00000000000000000001111000111011 &
b00000000000000000001011011010010 '
b00000000000000000001000100111010 (
#77
0#
#78
1#
b00000000000000000010100000001100 &
b00000000000000000001111000111011 '
b00000000000000000001011011010010 (
#79
0#
#80
1#
b00000000000000000011010100001101 &
b00000000000000000010100000001100 '
b00000000000000000001111000111011 (
#81
0#
#82
1#
b00000000000000000100011001000111 &
b00000000000000000011010100001101 '
b00000000000000000010100000001100 (
#83
0#
#84
1#
b00000000000000000101110100011001 &
b00000000000000000100011001000111 '
b00000000000000000011010100001101 (
#85
0#
#86
1#
b00000000000000000111101101010100 &
b00000000000000000101110100011001 '
b00000000000000000100011001000111 (
#87
0#
#88
1#
b00000000000000001010001101100000 &
b00000000000000000111101101010100 '
b00000000000000000101110100011001 (
#89
0#
#90
1#
b00000000000000001101100001101101 &
b00000000000000001010001101100000 '
b00000000000000000111101101010100 (
#91
0#
#92
1#
b00000000000000010001111010110100 &
b00000000000000001101100001101101 '
b00000000000000001010001101100000 (
#93
0#
#94
1#
b00000000000000010111101111001101 &
b00000000000000010001111010110100 '
b00000000000000001101100001101101 (
#95
0#
#96
1#
b00000000000000011111011100100001 &
b00000000000000010111101111001101 '
b00000000000000010001111010110100 (
#97
0#
#98
1#
b00000000000000101001101010000001 &
b00000000000000011111011100100001 '
b00000000000000010111101111001101 (
#99
0#
#100
1#
b00000000000000110111001011101110 &
b00000000000000101001101010000001 '
b00000000000000011111011100100001 (
#101
0#
#102
1#
b00000000000001001001000110100010 &
b00000000000000110111001011101110 '
b00000000000000101001101010000001 (
#103
0#
#104
1#
b00000000000001100000110101101111 &
b00000000000001001001000110100010 '
b00000000000000110111001011101110 (
#105
0#
#106
1#
b00000000000010000000010010010000 &
b00000000000001100000110101101111 '
b00000000000001001001000110100010 (
#107
0#
#108
1#
b00000000000010101001111100010001 &
b00000000000010000000010010010000 '
b00000000000001100000110101101111 (
#109
0#
#110
1#
b00000000000011100001000111111111 &
b00000000000010101001111100010001 '
b00000000000010000000010010010000 (
#111
0#
#112
1#
b00000000000100101010001110100001 &
b00000000000011100001000111111111 '
b00000000000010101001111100010001 (
#113
0#
#114
1#
b00000000000110001011000100010000 &
b00000000000100101010001110100001 '
b00000000000011100001000111111111 (
#115
0#
#116
1#
b00000000001000001011010110100000 &
b00000000000110001011000100010000 '
b00000000000100101010001110100001 (
#117
0#
#118
1#
b00000000001010110101010010110001 &
b00000000001000001011010110100000 '
b00000000000110001011000100010000 (
#119
0#
#120
1#
b00000000001110010110011010110000 &
b00000000001010110101010010110001 '
b00000000001000001011010110100000 (
#121
0#
#122
1#
b00000000010011000000101001010001 &
b00000000001110010110011010110000 '
b00000000001010110101010010110001 (
#123
0#
#124
1#
b00000000011001001011101101100001 &
b00000000010011000000101001010001 '
b00000000001110010110011010110000 (
#125
0#
#126
1#
b00000000100001010111000100000001 &
b00000000011001001011101101100001 '
b00000000010011000000101001010001 (
#127
0#
#128
1#
b00000000101100001100010110110010 &
b00000000100001010111000100000001 '
b00000000011001001011101101100001 (
#129
0#
#130
1#
b00000000111010100010110001100010 &
b00000000101100001100010110110010 '
b00000000100001010111000100000001 (
#131
0#
#132
1#
b00000001001101100011011010110011 &
b00000000111010100010110001100010 '
b00000000101100001100010110110010 (
#133
0#
#134
1#
b00000001100110101111001000010100 &
b00000001001101100011011010110011 '
b00000000111010100010110001100010 (
#135
0#
#136
1#
b00000010001000000110001100010101 &
b00000001100110101111001000010100 '
b00000001001101100011011010110011 (
#137
0#
#138
1#
b00000010110100010010100011000111 &
b00000010001000000110001100010101 '
b00000001100110101111001000010100 (
#139
0#
#140
1#
b00000011101110110101010100101001 &
b00000010110100010010100011000111 '
b00000010001000000110001100010101 (
#141
0#
#142
1#
b00000100111100011000101111011100 &
b00000011101110110101010100101001 '
b00000010110100010010100011000111 (
#143
0#
#144
1#
b00000110100011000111110111110000 &
b00000100111100011000101111011100 '
b00000011101110110101010100101001 (
#145
0#
#146
1#
b00001000101011001110000100000101 &
b00000110100011000111110111110000 '
b00000100111100011000101111011100 (
#147
0#
#148
1#
b00001011011111100000100111001100 &
b00001000101011001110000100000101 '
b00000110100011000111110111110000 (
#149
0#
#150
1#
b00001111001110010101111011110101 &
b00001011011111100000100111001100 '
b00001000101011001110000100000101 (
#151
0#
#152
1#
b00010100001010101110101011010001 &
b00001111001110010101111011110101 '
b00001011011111100000100111001100 (
#153
0#
#154
1#
b00011010101101110110100011000001 &
b00010100001010101110101011010001 '
b00001111001110010101111011110101 (
#155
0#
#156
1#
b00100011011001000100100111000110 &
b00011010101101110110100011000001 '
b00010100001010101110101011010001 (
#157
0#
#158
1#
b00101110111000100101001110010010 &
b00100011011001000100100111000110 '
b00011010101101110110100011000001 (
#159
0#
#160
1#
b00111110000110111011001010000111 &
b00101110111000100101001110010010 '
b00100011011001000100100111000110 (
#161
0#
#162
1#
b01010010010001101001110101011000 &
b00111110000110111011001010000111 '
b00101110111000100101001110010010 (
#163
0#
#164
1#
b01101100111111100000011000011001 &
b01010010010001101001110101011000 '
b00111110000110111011001010000111 (
#165
0#
#166
1#
b10010000011000100100111111011111 &
b01101100111111100000011000011001 '
b01010010010001101001110101011000 (
#167
0#
#168
1#
b10111111010001001010001101110001 &
b10010000011000100100111111011111 '
b01101100111111100000011000011001 (
#169
0#
#170
1#
b11111101011000000101010111111000 &
b10111111010001001010001101110001 '
b10010000011000100100111111011111 (
#171
0#
#172
1#
b01001111101001101111001101010000 &
b11111101011000000101010111111000 '
b10111111010001001010001101110001 (
#173
0#
#174
1#
b10111100101001001111100101101001 &
b01001111101001101111001101010000 '
b11111101011000000101010111111000 (
#175
0#
#176
1#
b01001101000001110100100101001000 &
b10111100101001001111100101101001 '
b01001111101001101111001101010000 (
#177
0#
#178
1#
b00001100010010111110110010111001 &
b01001101000001110100100101001000 '
b10111100101001001111100101101001 (
#179
0#
#180
1#
b00001001101011000100001010110001 &
b00001100010010111110110010111001 '
b01001101000001110100100101001000 (
#181
0#
#182
1#
b01011001010100110011011000000001 &
b00001001101011000100001010110001 '
b00001100010010111110110010111001 (
#183
0#
#184
1#
b00010101111110000010111101101010 &
b01011001010100110011011000000001 '
b00001001101011000100001010110001 (
#185
0#
#186
1#
b01100010111111110111100010110010 &
b00010101111110000010111101101010 '
b01011001010100110011011000000001 (
#187
0#
#188
1#
b01101111010010110110010101101011 &
b01100010111111110111100010110010 '
b00010101111110000010111101101010 (
#189
0#
#190
1#
b01111000111101111010100000011100 &
b01101111010010110110010101101011 '
b01100010111111110111100010110010 (
#191
0#
#192
1#
b11010010010010101101111000011101 &
b01111000111101111010100000011100 '
b01101111010010110110010101101011 (
#193
0#
#194
1#
b11101000010000110000110110000111 &
b11010010010010101101111000011101 '
b01111000111101111010100000011100 (
#195
0#
#196
1#
b01001011010000101000011000111001 &
b11101000010000110000110110000111 '
b11010010010010101101111000011101 (
#197
0#
#198
1#
b10111010100011011110101110100100 &
b01001011010000101000011000111001 '
b11101000010000110000110110000111 (
#199
0#
#200
1#
b00110011100001011001001111000000 &
b10111010100011011110101110100100 '
b01001011010000101000011000111001 (
#201
0#
#202
1#
b00000101110100000111000111011101 &
b00110011100001011001001111000000 '
b10111010100011011110101110100100 (
#203
0#
#204
1#
b11101110000100110111111101100100 &
b00000101110100000111000111011101 '
b00110011100001011001001111000000 (
#205
0#
#206
1#
b00111001010101100000010110011101 &
b11101110000100110111111101100100 '
b00000101110100000111000111011101 (
#207
0#
#208
1#
b11110011111000111111000101000001 &
b00111001010101100000010110011101 '
b11101110000100110111111101100100 (
#209
0#
#210
1#
b00100111011010011000010100000001 &
b11110011111000111111000101000001 '
b00111001010101100000010110011101 (
#211
0#
#212
1#
b00101101001110011111011011011110 &
b00100111011010011000010100000001 '
b11110011111000111111000101000001 (
#213
0#
#214
1#
b00011011010011010111011001000010 &
b00101101001110011111011011011110 '
b00100111011010011000010100000001 (
#215
0#
#216
1#
b01010100101000110111101111011111 &
b00011011010011010111011001000010 '
b00101101001110011111011011011110 (
#217
0#
#218
1#
b01001000100001110110110100100000 &
b01010100101000110111101111011111 '
b00011011010011010111011001000010 (
#219
0#
#220
1#
b01101111111100001111001000100001 &
b01001000100001110110110100100000 '
b01010100101000110111101111011111 (
#221
0#
#222
1#
b10011101001010101110100011111111 &
b01101111111100001111001000100001 '
b01001000100001110110110100100000 (
#223
0#
#224
1#
b10111000011110000101111101000001 &
b10011101001010101110100011111111 '
b01101111111100001111001000100001 (
#225
0#
#226
1#
b00001101000110111101101100100000 &
b10111000011110000101111101000001 '
b10011101001010101110100011111111 (
#227
0#
#228
1#
b01010101101000110100100001000000 &
b00001101000110111101101100100000 '
b10111000011110000101111101000001 (
#229
0#
#230
1#
b11000101100101000011101001100001 &
b01010101101000110100100001000000 '
b00001101000110111101101100100000 (
#231
0#
#232
1#
b01100010101111110010001101100000 &
b11000101100101000011101001100001 '
b01010101101000110100100001000000 (
#233
0#
#234
1#
b00011011001101111000001010100001 &
b01100010101111110010001101100000 '
b11000101100101000011101001100001 (
#235
0#
#236
1#
b00101000010100110101110111000001 &
b00011011001101111000001010100001 '
b01100010101111110010001101100000 (
#237
0#
#238
1#
b01111101111101101010011000000001 &
b00101000010100110101110111000001 '
b00011011001101111000001010100001 (
#239
0#
#240
1#
b01000011100010101110000001100010 &
b01111101111101101010011000000001 '
b00101000010100110101110111000001 (
#241
0#
#242
1#
b10100110010010100000001111000010 &
b01000011100010101110000001100010 '
b01111101111101101010011000000001 (
#243
0#
#244
1#
b11000001100000011000011001100011 &
b10100110010010100000001111000010 '
b01000011100010101110000001100010 (
#245
0#
#246
1#
b11101001110101001110010000100100 &
b11000001100000011000011001100011 '
b10100110010010100000001111000010 (
#247
0#
#248
1#
b01100111110010111000101000100101 &
b11101001110101001110010000100100 '
b11000001100000011000011001100011 (
#249
0#
#250
1#
b10101011010101100110101010000111 &
b01100111110010111000101000100101 '
b11101001110101001110010000100100 (
#251
0#
#252
1#
b01010001101000000110111001001001 &
b10101011010101100110101010000111 '
b01100111110010111000101000100101 (
#253
0#
#254
1#
b00010011001000011111010010101100 &
b01010001101000000110111001001001 '
b10101011010101100110101010000111 (
#255
0#
#256
1#
b11111100111101101101100011010000 &
b00010011001000011111010010101100 '
b01010001101000000110111001001001 (
#257
0#
#258
1#
b01100100110000100110001011110101 &
b11111100111101101101100011010000 '
b00010011001000011111010010101100 (
#259
0#
#260
1#
b00010000000110001100110101111100 &
b01100100110000100110001011110101 '
b11111100111101101101100011010000 (
#261
0#
#262
1#
b01100001101110010011101111000101 &
b00010000000110001100110101111100 '
b01100100110000100110001011110101 (
#263
0#
#264
1#
b01110100110110110011000001110001 &
b01100001101110010011101111000101 '
b00010000000110001100110101111100 (
#265
0#
#266
1#
b01110001110100100000100101000001 &
b01110100110110110011000001110001 '
b01100001101110010011101111000101 (
#267
0#
#268
1#
b11010110100101000110110000110110 &
b01110001110100100000100101000001 '
b01110100110110110011000001110001 (
#269
0#
#270
1#
b11100110101011010011100110110010 &
b11010110100101000110110000110110 '
b01110001110100100000100101000001 (
#271
0#
#272
1#
b01001000011001100111010101110111 &
b11100110101011010011100110110010 '
b11010110100101000110110000110110 (
#273
0#
#274
1#
b10111101010000011010010111101000 &
b01001000011001100111010101110111 '
b11100110101011010011100110110010 (
#275
0#
#276
1#
b00101111000100111010111100101001 &
b10111101010000011010010111101000 '
b01001000011001100111010101110111 (
#277
0#
#278
1#
b00000101101010000001101101011111 &
b00101111000100111010111100101001 '
b10111101010000011010010111101000 (
#279
0#
#280
1#
b11101100010101010101010100010001 &
b00000101101010000001101101011111 '
b00101111000100111010111100101001 (
#281
0#
#282
1#
b00110100101110111100101010001000 &
b11101100010101010101010100010001 '
b00000101101010000001101101011111 (
#283
0#
#284
1#
b11110001111111010111000001110000 &
b00110100101110111100101010001000 '
b11101100010101010101010100010001 (
#285
0#
#286
1#
b00100001000100010001111110011001 &
b11110001111111010111000001110000 '
b00110100101110111100101010001000 (
#287
0#
#288
1#
b00100110101110010011101011111000 &
b00100001000100010001111110011001 '
b11110001111111010111000001110000 (
#289
0#
#290
1#
b00010011000011101001000000001001 &
b00100110101110010011101011111000 '
b00100001000100010001111110011001 (
#291
0#
#292
1#
b01000111110010100101101010010001 &
b00010011000011101001000000001001 '
b00100110101110010011101011111000 (
#293
0#
#294
1#
b00111001110001111100101100000001 &
b01000111110010100101101010010001 '
b00010011000011101001000000001001 (
#295
0#
#296
1#
b01011010110110001110101010011010 &
b00111001110001111100101100000001 '
b01000111110010100101101010010001 (
#297
0#
#298
1#
b10000001100100100010010110010010 &
b01011010110110001110101010011010 '
b00111001110001111100101100000001 (
#299
0#
#300
1#
b10010100101000001011010110011011 &
b10000001100100100010010110010010 '
b01011010110110001110101010011010 (
#301
0#
#302
1#
b11011100011010110001000000101100 &
b10010100101000001011010110011011 '
b10000001100100100010010110010010 (
#303
0#
#304
1#
b00010110001100101101101100101101 &
b11011100011010110001000000101100 '
b10010100101000001011010110011011 (
#305
0#
#306
1#
b01110001000010111100010111000111 &
b00010110001100101101101100101101 '
b11011100011010110001000000101100 (
#307
0#
#308
1#
b11110010100111011110101101011001 &
b01110001000010111100010111000111 '
b00010110001100101101101100101101 (
#309
0#
#310
1#
b10000111001111101010000011110100 &
b11110010100111011110101101011001 '
b01110001000010111100010111000111 (
#311
0#
#312
1#
b01100011101010011011000100100000 &
b10000111001111101010000011110100 '
b11110010100111011110101101011001 (
#313
0#
#314
1#
b01111001110111001000110001001101 &
b01100011101010011011000100100000 '
b10000111001111101010000011110100 (
#315
0#
#316
1#
b11101010111010000101001000010100 &
b01111001110111001000110001001101 '
b01100011101010011011000100100000 (
#317
0#
#318
1#
b11011101100001100011110101101101 &
b11101010111010000101001000010100 '
b01111001110111001000110001001101 (
#319
0#
#320
1#
b01100100110001001101111001100001 &
b11011101100001100011110101101101 '
b11101010111010000101001000010100 (
#321
0#
#322
1#
b11001000011011101000111110000001 &
b01100100110001001101111001100001 '
b11011101100001100011110101101101 (
#323
0#
#324
1#
b01000010010010110001101111001110 &
b11001000011011101000111110000001 '
b01100100110001001101111001100001 (
#325
0#
#326
1#
b00101101001100110110110111100010 &
b01000010010010110001101111001110 '
b11001000011011101000111110000001 (
#327
0#
#328
1#
b00001010101110011010101101001111 &
b00101101001100110110110111100010 '
b01000010010010110001101111001110 (
#329
0#
#330
1#
b01101111011111101000100110110000 &
b00001010101110011010101101001111 '
b00101101001100110110110111100010 (
#331
0#
#332
1#
b00110111111011010001100100110001 &
b01101111011111101000100110110000 '
b00001010101110011010101101001111 (
#333
0#
#334
1#
b01111010001110000011010011111111 &
b00110111111011010001100100110001 '
b01101111011111101000100110110000 (
#335
0#
#336
1#
b10100111011010111010001011100001 &
b01111010001110000011010011111111 '
b00110111111011010001100100110001 (
#337
0#
#338
1#
b10110010001001010100111000110000 &
b10100111011010111010001011100001 '
b01111010001110000011010011111111 (
#339
0#
#340
1#
b00100001101000111101011111100000 &
b10110010001001010100111000110000 '
b10100111011010111010001011100001 (
#341
0#
#342
1#
b01011001100100001111000100010001 &
b00100001101000111101011111100000 '
b10110010001001010100111000110000 (
#343
0#
#344
1#
b11010011110010010010011000010000 &
b01011001100100001111000100010001 '
b00100001101000111101011111100000 (
#345
0#
#346
1#
b01111011001101001100100011110001 &
b11010011110010010010011000010000 '
b01011001100100001111000100010001 (
#347
0#
#348
1#
b00101101010110100001011100100001 &
b01111011001101001100100011110001 '
b11010011110010010010011000010000 (
#349
0#
#350
1#
b01001110111111011110111100000001 &
b00101101010110100001011100100001 '
b01111011001101001100100011110001 (
#351
0#
#352
1#
b10101000100011101110000000010010 &
b01001110111111011110111100000001 '
b00101101010110100001011100100001 (
#353
0#
#354
1#
b01111100010110000000011000100010 &
b10101000100011101110000000010010 '
b01001110111111011110111100000001 (
#355
0#
#356
1#
b11110111100011001100111100010011 &
b01111100010110000000011000100010 '
b10101000100011101110000000010010 (
#357
0#
#358
1#
b00100100111001101110011000110100 &
b11110111100011001100111100010011 '
b01111100010110000000011000100010 (
#359
0#
#360
1#
b01110011111001001101010100110101 &
b00100100111001101110011000110100 '
b11110111100011001100111100010011 (
#361
0#
#362
1#
b00011100011100111011010101000111 &
b01110011111001001101010100110101 '
b00100100111001101110011000110100 (
#363
0#
#364
1#
b10011000110010111011101101101001 &
b00011100011100111011010101000111 '
b01110011111001001101010100110101 (
#365
0#
#366
1#
b10010000010110001000101001111100 &
b10011000110010111011101101101001 '
b00011100011100111011010101000111 (
#367
0#
#368
1#
b10110101001111110111000010110000 &
b10010000010110001000101001111100 '
b10011000110010111011101101101001 (
#369
0#
#370
1#
b00101001001001000100010111100101 &
b10110101001111110111000010110000 '
b10010000010110001000101001111100 (
#371
0#
#372
1#
b01000101100101111111101100101100 &
b00101001001001000100010111100101 '
b10110101001111110111000010110000 (
#373
0#
#374
1#
b11011110011000111011011010010101 &
b01000101100101111111101100101100 '
b00101001001001000100010111100101 (
#375
0#
#376
1#
b01101110101111000100000100010001 &
b11011110011000111011011010010101 '
b01000101100101111111101100101100 (
#377
0#
#378
1#
b00100011111110111011000111000001 &
b01101110101111000100000100010001 '
b11011110011000111011011010010101 (
#379
0#
#380
1#
b01001101000111111111011110100110 &
b00100011111110111011000111000001 '
b01101110101111000100000100010001 (
#381
0#
#382
1#
b10010010101101111111001011010010 &
b01001101000111111111011110100110 '
b00100011111110111011000111000001 (
#383
0#
#384
1#
b01110001000110111010100101100111 &
b10010010101101111111001011010010 '
b01001101000111111111011110100110 (
#385
0#
#386
1#
b11011111110101111110101001111000 &
b01110001000110111010100101100111 '
b10010010101101111111001011010010 (
#387
0#
#388
1#
b00000011110100111001110000111001 &
b11011111110101111110101001111000 '
b01110001000110111010100101100111 (
#389
0#
#390
1#
b01010000111100111001001111011111 &
b00000011110100111001110000111001 '
b11011111110101111110101001111000 (
#391
0#
#392
1#
b11100011101010111000011010110001 &
b01010000111100111001001111011111 '
b00000011110100111001110000111001 (
#393
0#
#394
1#
b01010100110001110011000000011000 &
b11100011101010111000011010110001 '
b01010000111100111001001111011111 (
#395
0#
#396
1#
b00110100100111110001101010010000 &
b01010100110001110011000000011000 '
b11100011101010111000011010110001 (
#397
0#
#398
1#
b00111000011100101011011011001001 &
b00110100100111110001101010010000 '
b01010100110001110011000000011000 (
#399
0#
#400
1#
b10001001011001100100101010101000 &
b00111000011100101011011011001001 '
b00110100100111110001101010010000 (
#401
0#
#402
1#
b01101101000100011101000101011001 &
b10001001011001100100101010101000 '
b00111000011100101011011011001001 (
#403
0#
#404
1#
b11000001110110010000000101110001 &
b01101101000100011101000101011001 '
b10001001011001100100101010101000 (
#405
0#
#406
1#
b11110110011110000001110000000001 &
b11000001110110010000000101110001 '
b01101101000100011101000101011001 (
#407
0#
#408
1#
b00101110111010101101001011001010 &
b11110110011110000001110000000001 '
b11000001110110010000000101110001 (
#409
0#
#410
1#
b10111000010100010001110101110010 &
b00101110111010101101001011001010 '
b11110110011110000001110000000001 (
#411
0#
#412
1#
b00100101011000101110111011001011 &
b10111000010100010001110101110010 '
b00101110111010101101001011001010 (
#413
0#
#414
1#
b11100111001110111111000000111100 &
b00100101011000101110111011001011 '
b10111000010100010001110101110010 (
#415
0#
#416
1#
b11011101101101000000110000111101 &
b11100111001110111111000000111100 '
b00100101011000101110111011001011 (
#417
0#
#418
1#
b00001100100111101101111100000111 &
b11011101101101000000110000111101 '
b11100111001110111111000000111100 (
#419
0#
#420
1#
b11000100111011111111110001111001 &
b00001100100111101101111100000111 '
b11011101101101000000110000111101 (
#421
0#
#422
1#
b11101010010100101110101101000100 &
b11000100111011111111110001111001 '
b00001100100111101101111100000111 (
#423
0#
#424
1#
b11010001100011101101101110000000 &
b11101010010100101110101101000100 '
b11000100111011111111110001111001 (
#425
0#
#426
1#
b10101111010000101110011110111101 &
b11010001100011101101101110000000 '
b11101010010100101110101101000100 (
#427
0#
#428
1#
b10111011111000011100011011000100 &
b10101111010000101110011110111101 '
b11010001100011101101101110000000 (
#429
0#
#430
1#
b10000000110100011100001100111101 &
b10111011111000011100011011000100 '
b10101111010000101110011110111101 (
#431
0#
#432
1#
b01101011001001001010111010000001 &
b10000000110100011100001100111101 '
b10111011111000011100011011000100 (
#433
0#
#434
1#
b00111100101100111000101000000001 &
b01101011001001001010111010000001 '
b10000000110100011100001100111101 (
#435
0#
#436
1#
b11101011111101100111000110111110 &
b00111100101100111000101000000001 '
b01101011001001001010111010000001 (
#437
0#
#438
1#
b10100111110110000011100010000010 &
b11101011111101100111000110111110 '
b00111100101100111000101000000001 (
#439
0#
#440
1#
b00101000101010011111101110111111 &
b10100111110110000011100010000010 '
b11101011111101100111000110111110 (
#441
0#
#442
1#
b10010011110011101010101001000000 &
b00101000101010011111101110111111 '
b10100111110110000011100010000010 (
#443
0#
#444
1#
b11010000100000100011010001000001 &
b10010011110011101010101001000000 '
b00101000101010011111101110111111 (
#445
0#
#446
1#
b10111100011110001010010111111111 &
b11010000100000100011010001000001 '
b10010011110011101010101001000000 (
#447
0#
#448
1#
b01100100010100001101111010000001 &
b10111100011110001010010111111111 '
b11010000100000100011010001000001 (
#449
0#
#450
1#
b10001100111110101101101001000000 &
b01100100010100001101111010000001 '
b10111100011110001010010111111111 (
#451
0#
#452
1#
b00100000110010011000010010000000 &
b10001100111110101101101001000000 '
b01100100010100001101111010000001 (
#453
0#
#454
1#
b11110001010010111011100011000001 &
b00100000110010011000010010000000 '
b10001100111110101101101001000000 (
#455
0#
#456
1#
b10101101110001000101111011000000 &
b11110001010010111011100011000001 '
b00100000110010011000010010000000 (
#457
0#
#458
1#
b00010010000101010011110101000001 &
b10101101110001000101111011000000 '
b11110001010010111011100011000001 (
#459
0#
#460
1#
b10011111000100000001011110000001 &
b00010010000101010011110101000001 '
b10101101110001000101111011000000 (
#461
0#
#462
1#
b10111111110110011001110000000001 &
b10011111000100000001011110000001 '
b00010010000101010011110101000001 (
#463
0#
#464
1#
b10110001001001010101010011000010 &
b10111111110110011001110000000001 '
b10011111000100000001011110000001 (
#465
0#
#466
1#
b01011110111010011011001110000010 &
b10110001001001010101010011000010 '
b10111111110110011001110000000001 (
#467
0#
#468
1#
b01110000111111101111000011000011 &
b01011110111010011011001110000010 '
b10110001001001010101010011000010 (
#469
0#
#470
1#
b00010000000011110000100001000100 &
b01110000111111101111000011000011 '
b01011110111010011011001110000010 (
#471
0#
#472
1#
b11001111111010001010010001000101 &
b00010000000011110000100001000100 '
b01110000111111101111000011000011 (
#473
0#
#474
1#
b10000001000011011111100100000111 &
b11001111111010001010010001000101 '
b00010000000011110000100001000100 (
#475
0#
#476
1#
b11011111111101111010110010001001 &
b10000001000011011111100100000111 '
b11001111111010001010010001000101 (
#477
0#
#478
1#
b01010000111101101001110101001100 &
b11011111111101111010110010001001 '
b10000001000011011111100100000111 (
#479
0#
#480
1#
b01100001000001011010010110010000 &
b01010000111101101001110101001100 '
b11011111111101111010110010001001 (
#481
0#
#482
1#
b00110000111011100100100111010101 &
b01100001000001011010010110010000 '
b01010000111101101001110101001100 (
#483
0#
#484
1#
b10110001111111000100001011011100 &
b00110000111011100100100111010101 '
b01100001000001011010010110010000 (
#485
0#
#486
1#
b10010001111100111110111101100101 &
b10110001111111000100001011011100 '
b00110000111011100100100111010101 (
#487
0#
#488
1#
b11100010111010101000110010110001 &
b10010001111100111110111101100101 '
b10110001111111000100001011011100 (
#489
0#
#490
1#
b01000011111100000011001001000001 &
b11100010111010101000110010110001 '
b10010001111100111110111101100101 (
#491
0#
#492
1#
b01110100110111100111110000010110 &
b01000011111100000011001001000001 '
b11100010111010101000110010110001 (
#493
0#
#494
1#
b00100110110110101011111011110010 &
b01110100110111100111110000010110 '
b01000011111100000011001001000001 (
#495
0#
#496
1#
b10111000110011101010111001010111 &
b00100110110110101011111011110010 '
b01110100110111100111110000010110 (
#497
0#
#498
1#
b10011011101110010011101100001000 &
b10111000110011101010111001010111 '
b00100110110110101011111011110010 (
#499
0#
#500
1#
b11011111101010010110110101001001 &
b10011011101110010011101100001000 '
b10111000110011101010111001010111 (
#501
0#
#502
1#
b01010100100001111110100101011111 &
b11011111101010010110110101001001 '
b10011011101110010011101100001000 (
#503
0#
#504
1#
b01111011011000101010100001010001 &
b01010100100001111110100101011111 '
b11011111101010010110110101001001 (
#505
0#
#506
1#
b00110100001100010101011010101000 &
b01111011011000101010100001010001 '
b01010100100001111110100101011111 (
#507
0#
#508
1#
b11001111111010101001000110110000 &
b00110100001100010101011010101000 '
b01111011011000101010100001010001 (
#509
0#
#510
1#
b10101111100100111111111011111001 &
b11001111111010101001000110110000 '
b00110100001100010101011010101000 (
#511
0#
#512
1#
b00000100000110111110100001011000 &
b10101111100100111111111011111001 '
b11001111111010101001000110110000 (
#513
0#
#514
1#
b01111111011111101001000010101001 &
b00000100000110111110100001011000 '
b10101111100100111111111011111001 (
#515
0#
